incaricli/__init__.py
incaricli/cli.py
incaricli-0.2.1.dist-info/licenses/LICENSE
incaricli-0.2.1.dist-info/METADATA
incaricli-0.2.1.dist-info/WHEEL
incaricli-0.2.1.dist-info/entry_points.txt
incaricli-0.2.1.dist-info/top_level.txt
incaricli-0.2.1.dist-info/RECORD
