Metadata-Version: 2.4
Name: incaricli
Version: 0.2.1
Summary: A simple and elegant task manager for your command line
Author-email: Paolo Bietolini <chat@paolobietolini.com>
License: MIT
Project-URL: Homepage, https://github.com/paolobtl/incaricli
Project-URL: Repository, https://github.com/paolobtl/incaricli
Project-URL: Bug Tracker, https://github.com/paolobtl/incaricli/issues
Keywords: cli,task-manager,todo,productivity,terminal
Classifier: Development Status :: 3 - Alpha
Classifier: Intended Audience :: Developers
Classifier: Intended Audience :: End Users/Desktop
Classifier: License :: OSI Approved :: MIT License
Classifier: Operating System :: OS Independent
Classifier: Programming Language :: Python :: 3
Classifier: Programming Language :: Python :: 3.10
Classifier: Programming Language :: Python :: 3.11
Classifier: Programming Language :: Python :: 3.12
Classifier: Topic :: Utilities
Classifier: Topic :: Office/Business
Classifier: Environment :: Console
Requires-Python: >=3.10
License-File: LICENSE
Requires-Dist: rich>=13.0.0
Provides-Extra: dev
Requires-Dist: pytest>=7.0.0; extra == "dev"
Requires-Dist: pytest-cov>=4.0.0; extra == "dev"
Requires-Dist: black>=23.0.0; extra == "dev"
Requires-Dist: ruff>=0.1.0; extra == "dev"
Requires-Dist: mypy>=1.0.0; extra == "dev"
Dynamic: license-file
